fabisschomagut/LICENSE
fabisschomagut/README.md
fabisschomagut/__init__.py
fabisschomagut/requirements.txt
fabisschomagut/thirdparty.json
fabisschomagut-0.10.dist-info/LICENSE.rst
fabisschomagut-0.10.dist-info/METADATA
fabisschomagut-0.10.dist-info/WHEEL
fabisschomagut-0.10.dist-info/top_level.txt
fabisschomagut-0.10.dist-info/RECORD
