Metadata-Version: 2.1
Name: fabisschomagut
Version: 0.10
Summary: Converts back and forth between different color formats [(255,0,0),#ff0000, 16711680,(255,0,255) ... ]
Home-page: https://github.com/hansalemaos/fabisschomagut
Author: Johannes Fischer
Author-email: aulasparticularesdealemaosp@gmail.com
License: MIT
Keywords: rgb,bgr,bgra,convert
Classifier: Development Status :: 4 - Beta
Classifier: Programming Language :: Python :: 3 :: Only
Classifier: Programming Language :: Python :: 3.10
Classifier: Topic :: Software Development :: Libraries :: Python Modules
Classifier: Topic :: Utilities
License-File: LICENSE.rst
